odoo8_addon_runbot_coverage-8.0.1.0.0-py2.7-nspkg.pth
odoo8_addon_runbot_coverage-8.0.1.0.0.dist-info/DESCRIPTION.rst
odoo8_addon_runbot_coverage-8.0.1.0.0.dist-info/METADATA
odoo8_addon_runbot_coverage-8.0.1.0.0.dist-info/RECORD
odoo8_addon_runbot_coverage-8.0.1.0.0.dist-info/WHEEL
odoo8_addon_runbot_coverage-8.0.1.0.0.dist-info/metadata.json
odoo8_addon_runbot_coverage-8.0.1.0.0.dist-info/namespace_packages.txt
odoo8_addon_runbot_coverage-8.0.1.0.0.dist-info/top_level.txt
odoo_addons/runbot_coverage/README.rst
odoo_addons/runbot_coverage/__init__.py
odoo_addons/runbot_coverage/__openerp__.py
odoo_addons/runbot_coverage/controllers/__init__.py
odoo_addons/runbot_coverage/controllers/main.py
odoo_addons/runbot_coverage/models/__init__.py
odoo_addons/runbot_coverage/models/runbot_build.py
odoo_addons/runbot_coverage/models/runbot_repo.py
odoo_addons/runbot_coverage/static/description/icon.png
odoo_addons/runbot_coverage/views/runbot_repo.xml
odoo_addons/runbot_coverage/views/templates.xml
